obsidianflow/__init__.py
obsidianflow/client.py
obsidianflow-0.0.1.dist-info/METADATA
obsidianflow-0.0.1.dist-info/WHEEL
obsidianflow-0.0.1.dist-info/top_level.txt
obsidianflow-0.0.1.dist-info/RECORD
