Metadata-Version: 2.1
Name: obsidianflow
Version: 0.0.1
Summary: Supercharge your business with AI
Author: davnords
Author-email: david.nordstromm@gmail.com
Keywords: python,ai
